{
  "posts": [
    {
      "data": {
        "body": "1",
        "author": "john.doe@gmail.com",
        "created": 1721765896403,
        "edited": 1721765959431,
        "postId": "lc5n4q"
      },
      "id": 8
    },
    {
      "data": {
        "body": "3dfdfd",
        "author": "john.doe@gmail.com",
        "created": 1721766019407,
        "edited": 1721766019407,
        "postId": "zujql4"
      },
      "id": 9
    },
    {
      "data": {
        "body": "fdfvfv",
        "author": "john.doe@gmail.com",
        "created": 1721766030109,
        "edited": 1721766030109,
        "postId": "g08tea"
      },
      "id": 10
    },
    {
      "data": {
        "body": "l...rr4re3e3d4r4r4r4r4r4",
        "author": "john.doe@gmail.com",
        "created": 1721766092190,
        "edited": 1721766118106,
        "postId": "fijmzu"
      },
      "id": 12
    }
  ]
}